quarto_lib-4.0.1.dist-info/METADATA
quarto_lib-4.0.1.dist-info/WHEEL
quarto_lib-4.0.1.dist-info/entry_points.txt
quarto_lib-4.0.1.dist-info/licenses/LICENSE
quarto_lib/__init__.py
quarto_lib/arena.py
quarto_lib/contracts/__init__.py
quarto_lib/contracts/models.py
quarto_lib/contracts/quarto_agents.py
quarto_lib/game.py
quarto_lib/py.typed
quarto_lib/tournament_round.py
quarto_lib/types/__init__.py
quarto_lib/types/cell.py
quarto_lib/types/piece.py
quarto_lib/types/turn.py
quarto_lib/utils.py
quarto_lib-4.0.1.dist-info/RECORD
