Metadata-Version: 2.1
Name: quarto-lib
Version: 4.0.1
Summary: Common library for Quarto-Games projects.
Author-Email: patapelada <77882237+patapelada@users.noreply.github.com>
License: MIT
Project-URL: Homepage, https://github.com/patapelada/quarto-lib
Project-URL: Issues, https://github.com/patapelada/quarto-lib/issues
Requires-Python: ==3.13.*
Requires-Dist: pydantic>=2.11.7
